{
    "data": {
        "BTC-USDT": {
            "15min": {
                "price": 114104.98,
                "EMA_13": 113964.3127,
                "SMA_13": 113986.57,
                "EMA_49": 113969.772,
                "SMA_49": 114059.6841,
                "EMA_100": 113690.6821,
                "SMA_100": 113904.8436,
                "EMA_200": 113152.8265,
                "SMA_200": 112809.9068,
                "EMA_500": 112276.9757,
                "SMA_500": 111922.6972,
                "EMA_1000": 111778.3943,
                "SMA_1000": 111281.9099
            },
            "30min": {
                "price": 114104.98,
                "EMA_13": 114022.9555,
                "SMA_13": 114020.0492,
                "EMA_49": 113710.7047,
                "SMA_49": 113913.4694,
                "EMA_100": 113153.8955,
                "SMA_100": 112805.7635,
                "EMA_200": 112494.4158,
                "SMA_200": 112262.8718,
                "EMA_500": 111779.3224,
                "SMA_500": 111287.6548,
                "EMA_1000": 112148.3523,
                "SMA_1000": 111510.0516
            },
            "1hour": {
                "price": 113857.99,
                "EMA_13": 113955.4132,
                "SMA_13": 114035.3192,
                "EMA_49": 113150.606,
                "SMA_49": 112784.9006,
                "EMA_100": 112473.6296,
                "SMA_100": 112230.026,
                "EMA_200": 111868.5816,
                "SMA_200": 111646.666,
                "EMA_500": 112148.7169,
                "SMA_500": 111520.7154,
                "EMA_1000": 112954.5855,
                "SMA_1000": 113990.2387
            },
            "2hour": {
                "price": 114088.44,
                "EMA_13": 113658.6802,
                "SMA_13": 113823.0023,
                "EMA_49": 112463.6117,
                "SMA_49": 112199.8549,
                "EMA_100": 111843.9834,
                "SMA_100": 111631.2752,
                "EMA_200": 111897.4166,
                "SMA_200": 110871.8038,
                "EMA_500": 112950.5949,
                "SMA_500": 113988.9213,
                "EMA_1000": 111752.0797,
                "SMA_1000": 113335.671
            },
            "4hour": {
                "price": 114088.44,
                "EMA_13": 113117.1001,
                "SMA_13": 112735.7146,
                "EMA_49": 111872.6659,
                "SMA_49": 111673.0212,
                "EMA_100": 111902.4068,
                "SMA_100": 110894.0448,
                "EMA_200": 112764.0954,
                "SMA_200": 113768.596,
                "EMA_500": 111750.1079,
                "SMA_500": 113334.0065,
                "EMA_1000": 106775.2587,
                "SMA_1000": 105196.3148
            },
            "daily": {
                "price": 113848.7,
                "EMA_13": 111627.3045,
                "SMA_13": 110555.9223,
                "EMA_49": 112940.9295,
                "SMA_49": 114535.1392,
                "EMA_100": 110898.7525,
                "SMA_100": 112195.9168,
                "EMA_200": 104838.1711,
                "SMA_200": 102074.0766,
                "EMA_500": 88466.2562,
                "SMA_500": 86206.026,
                "EMA_1000": 71930.1748,
                "SMA_1000": 60673.8846
            }
        },
        "ETH-USDT": {
            "15min": {
                "price": 4417.82,
                "EMA_13": 4421.5766,
                "SMA_13": 4424.7262,
                "EMA_49": 4411.1926,
                "SMA_49": 4414.7792,
                "EMA_100": 4390.1198,
                "SMA_100": 4387.8887,
                "EMA_200": 4365.6732,
                "SMA_200": 4350.3973,
                "EMA_500": 4344.6903,
                "SMA_500": 4322.7493,
                "EMA_1000": 4355.4367,
                "SMA_1000": 4340.9422
            },
            "30min": {
                "price": 4417.81,
                "EMA_13": 4419.9669,
                "SMA_13": 4425.6362,
                "EMA_49": 4390.4105,
                "SMA_49": 4387.129,
                "EMA_100": 4365.2233,
                "SMA_100": 4349.8463,
                "EMA_200": 4346.5571,
                "SMA_200": 4330.8702,
                "EMA_500": 4355.2144,
                "SMA_500": 4340.8128,
                "EMA_1000": 4352.7377,
                "SMA_1000": 4437.6978
            },
            "1hour": {
                "price": 4409.27,
                "EMA_13": 4408.8847,
                "SMA_13": 4410.5254,
                "EMA_49": 4365.3053,
                "SMA_49": 4349.4139,
                "EMA_100": 4345.944,
                "SMA_100": 4329.7746,
                "EMA_200": 4348.7633,
                "SMA_200": 4337.8554,
                "EMA_500": 4352.6618,
                "SMA_500": 4437.7659,
                "EMA_1000": 4190.7495,
                "SMA_1000": 4266.9108
            },
            "2hour": {
                "price": 4432.76,
                "EMA_13": 4388.1888,
                "SMA_13": 4384.6915,
                "EMA_49": 4345.094,
                "SMA_49": 4328.0463,
                "EMA_100": 4347.6765,
                "SMA_100": 4337.3645,
                "EMA_200": 4361.5334,
                "SMA_200": 4387.1605,
                "EMA_500": 4190.5883,
                "SMA_500": 4266.9659,
                "EMA_1000": 3783.273,
                "SMA_1000": 3633.6373
            },
            "4hour": {
                "price": 4432.76,
                "EMA_13": 4368.0699,
                "SMA_13": 4350.9538,
                "EMA_49": 4348.2946,
                "SMA_49": 4338.7816,
                "EMA_100": 4361.1474,
                "SMA_100": 4386.4627,
                "EMA_200": 4269.2576,
                "SMA_200": 4417.0193,
                "EMA_500": 3783.9245,
                "SMA_500": 3635.1415,
                "EMA_1000": 3321.4408,
                "SMA_1000": 2893.1282
            },
            "daily": {
                "price": 4376.89,
                "EMA_13": 4346.7801,
                "SMA_13": 4327.1862,
                "EMA_49": 4115.2103,
                "SMA_49": 4196.7716,
                "EMA_100": 3660.499,
                "SMA_100": 3469.6317,
                "EMA_200": 3233.4714,
                "SMA_200": 2767.298,
                "EMA_500": 2912.202,
                "SMA_500": 2947.7885,
                "EMA_1000": 2745.4957,
                "SMA_1000": 2507.0711
            }
        }
    },
    "last_updated": "2025-09-11T13:42:08.082468+00:00"
}